dailypublisherrevenue/__init__.py
dailypublisherrevenue/dailyrevenue.py
dailypublisherspend-1.0.dist-info/METADATA
dailypublisherspend-1.0.dist-info/WHEEL
dailypublisherspend-1.0.dist-info/top_level.txt
dailypublisherspend-1.0.dist-info/RECORD
